betting/__init__.py
betting/example.py
betting/py.typed
pybetting-0.0.2.dist-info/METADATA
pybetting-0.0.2.dist-info/WHEEL
pybetting-0.0.2.dist-info/RECORD
